bk_bscp/__init__.py
bk_bscp/client.py
bk_bscp/constants.py
bk_bscp/exceptions.py
bk_bscp/models.py
bk_bscp/utils.py
tests/__init__.py
tests/conftest.py
tests/test_client_integrated.py
tests/test_utils.py
bscp_sdk_test-0.0.4.dist-info/LICENSE.txt
bscp_sdk_test-0.0.4.dist-info/METADATA
bscp_sdk_test-0.0.4.dist-info/WHEEL
bscp_sdk_test-0.0.4.dist-info/top_level.txt
bscp_sdk_test-0.0.4.dist-info/zip-safe
bscp_sdk_test-0.0.4.dist-info/RECORD
