Metadata-Version: 2.1
Name: bscp-sdk-test
Version: 0.0.4
Summary: The Python SDK for blueking bscp project.
Home-page: https://github.com/TencentBlueKing/bscp-python-sdk
Author: blueking
Author-email: blueking@tencent.com
Keywords: python,bscp
Classifier: Programming Language :: Python :: 3
Classifier: License :: OSI Approved :: MIT License
Requires-Python: >=3.8
License-File: LICENSE.txt
Requires-Dist: grpcio >=1.60.0
Requires-Dist: typing-extensions >=4.9.0
Requires-Dist: protobuf >=4.25.2
Provides-Extra: dev
Requires-Dist: grpcio-tools >=1.60.0 ; extra == 'dev'
Requires-Dist: ruff >=0.1.13 ; extra == 'dev'
Requires-Dist: pytest >=7.4.4 ; extra == 'dev'
Requires-Dist: mypy >=0.910 ; extra == 'dev'
